Metadata-Version: 2.1
Name: hehey-hupload
Version: 1.0.0
Summary: hehey-hupload 是一个python 文件上传工具类
Home-page: https://gitee.com/chinahehe/hehey-hupload
Author: 13564768842
Author-email: chinabluexfw@163.com
License: UNKNOWN
Platform: UNKNOWN
